NoteSaver
